planetaryimage/__init__.py
planetaryimage/cubefile.py
planetaryimage/decoders.py
planetaryimage/image.py
planetaryimage/pds3image.py
planetaryimage/specialpixels.py
planetaryimage-0.5.0.dist-info/DESCRIPTION.rst
planetaryimage-0.5.0.dist-info/METADATA
planetaryimage-0.5.0.dist-info/metadata.json
planetaryimage-0.5.0.dist-info/RECORD
planetaryimage-0.5.0.dist-info/top_level.txt
planetaryimage-0.5.0.dist-info/WHEEL
