Metadata-Version: 2.0
Name: planetaryimage
Version: 0.5.0
Summary: Planetary image parser supporting
Home-page: https://github.com/planetarypy/planetaryimage
Author: PlanetaryPy Developers
Author-email: contact@planetarypy.com
License: BSD
Keywords: planetaryimage
Platform: UNKNOWN
Classifier: Development Status :: 2 - Pre-Alpha
Classifier: Intended Audience :: Developers
Classifier: License :: OSI Approved :: BSD License
Classifier: Natural Language :: English
Classifier: Programming Language :: Python :: 2
Classifier: Programming Language :: Python :: 2.6
Classifier: Programming Language :: Python :: 2.7
Classifier: Programming Language :: Python :: 3
Classifier: Programming Language :: Python :: 3.3
Classifier: Programming Language :: Python :: 3.4
Classifier: Programming Language :: Python :: 3.5
Requires-Dist: numpy
Requires-Dist: pvl
Requires-Dist: six
